hyperscript/__init__.py
hyperscript/_version.py
hyperscript/element.py
hyperscript-0.3.0.dist-info/LICENSE
hyperscript-0.3.0.dist-info/METADATA
hyperscript-0.3.0.dist-info/WHEEL
hyperscript-0.3.0.dist-info/top_level.txt
hyperscript-0.3.0.dist-info/RECORD
