Metadata-Version: 2.1
Name: hyperscript
Version: 0.3.0
Summary: HyperText with Python
Author-email: Vincent Chan <vincent@qualdata.io>
License: MIT License
Project-URL: Homepage, https://github.com/vchan/hyperscript
Project-URL: Bug Tracker, https://github.com/vchan/hyperscript/issues
Classifier: Programming Language :: Python :: 3
Classifier: License :: OSI Approved :: MIT License
Classifier: Operating System :: OS Independent
Classifier: Intended Audience :: Developers
Classifier: Topic :: Text Processing :: Markup :: HTML
Requires-Python: >=3.8
License-File: LICENSE
Provides-Extra: dev
Requires-Dist: pre-commit; extra == "dev"
